onde/__init__.py
onde/onde.py
onde-0.1.1.dist-info/DESCRIPTION.rst
onde-0.1.1.dist-info/METADATA
onde-0.1.1.dist-info/RECORD
onde-0.1.1.dist-info/WHEEL
onde-0.1.1.dist-info/metadata.json
onde-0.1.1.dist-info/top_level.txt
