Metadata-Version: 2.0
Name: onde
Version: 0.1.1
Summary: A tool for giving meaningful names to file and directory paths
Home-page: https://github.com/phrasemix/onde
Author: Aaron Knight
Author-email: iamaaronknight@gmail.com
License: MIT
Platform: UNKNOWN
Requires-Dist: pyyaml
